emg3d/__init__.py
emg3d/__main__.py
emg3d/_multiprocessing.py
emg3d/core.py
emg3d/electrodes.py
emg3d/fields.py
emg3d/io.py
emg3d/maps.py
emg3d/meshes.py
emg3d/models.py
emg3d/simulations.py
emg3d/solver.py
emg3d/surveys.py
emg3d/time.py
emg3d/utils.py
emg3d/version.py
emg3d/cli/__init__.py
emg3d/cli/main.py
emg3d/cli/parser.py
emg3d/cli/run.py
emg3d/inversion/__init__.py
emg3d/inversion/pygimli.py
emg3d/inversion/simpeg.py
emg3d-1.8.7.dist-info/LICENSE
emg3d-1.8.7.dist-info/METADATA
emg3d-1.8.7.dist-info/WHEEL
emg3d-1.8.7.dist-info/entry_points.txt
emg3d-1.8.7.dist-info/top_level.txt
emg3d-1.8.7.dist-info/RECORD
