Metadata-Version: 2.2
Name: emg3d
Version: 1.8.7
Summary: A multigrid solver for 3D electromagnetic diffusion
Author-email: The emsig community <info@emsig.xyz>
License:                                  Apache License
Project-URL: Homepage, https://emsig.xyz
Project-URL: Documentation, https://emg3d.emsig.xyz
Project-URL: Repository, https://github.com/emsig/emg3d
Classifier: Development Status :: 5 - Production/Stable
Classifier: License :: OSI Approved :: Apache Software License
Classifier: Programming Language :: Python
Requires-Python: >=3.10
License-File: LICENSE
Requires-Dist: numpy
Requires-Dist: scipy>=1.10
Requires-Dist: numba
Requires-Dist: empymod>=2.3.2
Provides-Extra: full
Requires-Dist: tqdm; extra == "full"
Requires-Dist: h5py; extra == "full"
Requires-Dist: xarray; extra == "full"
Requires-Dist: discretize; extra == "full"
Requires-Dist: matplotlib; extra == "full"
Requires-Dist: ipympl; extra == "full"
Provides-Extra: docs
Requires-Dist: emg3d[full]; extra == "docs"
Requires-Dist: sphinx; extra == "docs"
Requires-Dist: numpydoc; extra == "docs"
Requires-Dist: ipykernel; extra == "docs"
Requires-Dist: pickleshare; extra == "docs"
Requires-Dist: sphinx_design; extra == "docs"
Requires-Dist: sphinx_numfig; extra == "docs"
Requires-Dist: sphinx_automodapi; extra == "docs"
Requires-Dist: pydata_sphinx_theme; extra == "docs"
Provides-Extra: tests
Requires-Dist: flake8; extra == "tests"
Requires-Dist: pytest; extra == "tests"
Requires-Dist: coveralls; extra == "tests"
Requires-Dist: pytest_cov; extra == "tests"
Requires-Dist: flake8-pyproject; extra == "tests"
Requires-Dist: pytest-console-scripts; extra == "tests"
Provides-Extra: all
Requires-Dist: emg3d[docs]; extra == "all"
Requires-Dist: emg3d[tests]; extra == "all"
Provides-Extra: build
Requires-Dist: setuptools_scm>=8; extra == "build"
Requires-Dist: setuptools>=64; extra == "build"
